[
	{
		"id": 1,
		"name": "Top category", 
		"parent_id": 0
	}, 
	{
		"id": 2, 
		"name": "Subcategory", 
		"parent_id": 0
	},
	{
		"id": 3,
		"name": "Top category", 
		"parent_id": 0
	}, 
	{
		"id": 4, 
		"name": "Subcategory", 
		"parent_id": 1
	},
	{
		"id": 5,
		"name": "Top category", 
		"parent_id": 1
	},
	{
		"id": 6,
		"name": "Top category", 
		"parent_id": 0
	}, 
	{
		"id": 7, 
		"name": "Subcategory", 
		"parent_id": 0
	},
	{
		"id": 8,
		"name": "Top category", 
		"parent_id": 0
	}, 
	{
		"id": 9, 
		"name": "Subcategory", 
		"parent_id": 1
	},
	{
		"id": 10,
		"name": "Top category", 
		"parent_id": 1
	},
	{
		"id": 11,
		"name": "Top category", 
		"parent_id": 0
	}, 
	{
		"id": 12, 
		"name": "Subcategory", 
		"parent_id": 0
	},
	{
		"id": 13,
		"name": "Top category", 
		"parent_id": 0
	}, 
	{
		"id": 14, 
		"name": "Subcategory", 
		"parent_id": 1
	},
	{
		"id": 15,
		"name": "Top category", 
		"parent_id": 1
	}

]